pp_onnx/__init__.py
pp_onnx/cls_postprocess.py
pp_onnx/db_postprocess.py
pp_onnx/imaug.py
pp_onnx/logger.py
pp_onnx/onnx_paddleocr.py
pp_onnx/operators.py
pp_onnx/predict_base.py
pp_onnx/predict_cls.py
pp_onnx/predict_det.py
pp_onnx/predict_rec.py
pp_onnx/predict_system.py
pp_onnx/rec_postprocess.py
pp_onnx/setup.py
pp_onnx/utils.py
pp_onnx/legancy/utils copy.py
pp_onnx/models/ch_PP-OCRv4_det_infer.onnx
pp_onnx/models/ch_PP-OCRv4_rec_infer.onnx
pp_onnx/models/cls.onnx
pp_onnx/models/ppocr_keys_v1.txt
pp_onnx/models/simfang.ttf
pp_onnx-0.1.3.dist-info/METADATA
pp_onnx-0.1.3.dist-info/WHEEL
pp_onnx-0.1.3.dist-info/top_level.txt
pp_onnx-0.1.3.dist-info/RECORD
